{
  "lastUpdated": "2026-06-27T19:02:38.450Z",
  "formulas": [
    {
      "id": "f_cabinet_parts",
      "file_name": "sheenhoong_Cabinet_Cut_List.json",
      "version": 1,
      "category": "Public",
      "name": {
        "zh": "Cabinet Cut List",
        "en": "Cabinet Cut List",
        "ms": ""
      },
      "remarks": {
        "zh": "Calculates board sizes for a cabinet. [Width], [Height],[Depth] is total Measurement, [BoardThick] is Top, Bottom and Side Board material thickness, [BackBoardThick] is Background Board material thickness.",
        "en": "Calculates board sizes for a cabinet. [Width], [Height],[Depth] is total Measurement, [BoardThick] is Top, Bottom and Side Board material thickness, [BackBoardThick] is Background Board material thickness.",
        "ms": ""
      },
      "factors": [
        {
          "id": "Width",
          "label": {
            "zh": "Width",
            "en": "Width",
            "ms": ""
          },
          "unit": null,
          "defaultValue": 0
        },
        {
          "id": "Height",
          "label": {
            "zh": "Height",
            "en": "Height",
            "ms": ""
          },
          "unit": null,
          "defaultValue": 0
        },
        {
          "id": "Depth",
          "label": {
            "zh": "Depth",
            "en": "Depth",
            "ms": ""
          },
          "unit": null,
          "defaultValue": 0
        },
        {
          "id": "BoardThick",
          "label": {
            "zh": "BoardThick",
            "en": "BoardThick",
            "ms": ""
          },
          "unit": null,
          "defaultValue": 0
        },
        {
          "id": "BackBoardThick",
          "label": {
            "zh": "BackBoardThick",
            "en": "BackBoardThick",
            "ms": ""
          },
          "unit": null,
          "defaultValue": 0
        }
      ],
      "expression": "Top''/Bottom Board: {([Width]) - 2 * ([BoardThick])} x {([Depth])-([BackBoardThick])} x {[BoardThick]} x 2pcs & Side Board: {([Height])} x {([Depth])-([BackBoardThick])} x {[BoardThick]} x 2pcs & Back Board: {([Width])} x {([Height])} x {([BackBoardThick])} x 1pcs",
      "author": "sheenhoong",
      "authorUid": "uladk5rR9kOZzNudZIV2ISYvWaD2",
      "rating": 0
    },
    {
      "id": "f_window_parts",
      "file_name": "sheenhoong_Window_Details.json",
      "version": 1,
      "category": "Public",
      "name": {
        "zh": "Window Details",
        "en": "Window Details",
        "ms": ""
      },
      "remarks": {
        "zh": "Example of multi-line output for window fabrication. Adjust offsets as needed.",
        "en": "Example of multi-line output for window fabrication. Adjust offsets as needed.",
        "ms": ""
      },
      "factors": [
        {
          "id": "W",
          "label": {
            "zh": "W",
            "en": "W",
            "ms": ""
          },
          "unit": null,
          "defaultValue": 0
        },
        {
          "id": "H",
          "label": {
            "zh": "H",
            "en": "H",
            "ms": ""
          },
          "unit": null,
          "defaultValue": 0
        }
      ],
      "expression": "Frame Size: {[W]} x {[H]} & Glass Size: {[W]-50mm} x {[H]-50mm} & Seal Length: {([W]+[H])*2}",
      "author": "sheenhoong",
      "authorUid": "uladk5rR9kOZzNudZIV2ISYvWaD2",
      "rating": 0
    }
  ]
}